<entry><div id="p066v_1" categories="medicine">
        
<head><md>Garder de croistre les <bp>tetins</bp><lb/>
            
<add><del>d</del> ou diminuer les trop
grands</add></md><comment rid="c_066v_03"/></head>
        
<ab>Ayes de <m>grands pains nouvellement tirés du <tl>four</tl></m>
&amp; les<lb/>
            
partes <ms>par moictié</ms>, &amp; le plus chauld que fere se
pourra,<lb/>
            
apliques les dessus <del>&amp; ilz</del> &amp; faictes cela 3 <ms>fois
le <tmp>jour</tmp></ms>,<lb/>
            
&amp; continues 4 ou 5 <ms><tmp>jours</tmp></ms>. Aprés, faictes
emplastre de<lb/>
            
<m>tourmentine de <pl>Venise</pl></m> ou pour mieulx de <m>tourmentine
commune</m>,<lb/>
            
mesles y du <m><pa>sumach</pa></m>, des <m><pa>prunelles de
buissons</pa></m>, de la <m>graine<lb/>
                    
de <pa>coings</pa></m>, <m><pa>balaustes</pa></m>, <m>foeilles
d'<pa>olivier</pa></m>, &amp; semblables<lb/>
            
decuits, &amp; mesles avecq la <m>tourmentine</m>. Mays j'oublyois<lb/>
            
qu'il fault aprés avoir apliqué le <m>pain chault</m> qui <md>ramolist</md>,<lb/>
            
&amp; <md>faict suer</md>, mectre dessus des <tl>linges trempés en <m>eau de
ruche de<lb/>
                
miel</m></tl>, c'est à scavoir de <m>miel</m> &amp; <m>cire</m>
extraicts tout ensemble du<lb/>
            
<oc>bornat</oc>.</ab>
        
</div>
    
    
 
</entry>