<entry><div categories="painting" id="p065r_1">
 Umbres
 <ab>
  Pource que les noirs font diverses couleurs, les uns un noir
rougeastre,
  <lb>
  </lb>
  les aultres tirant sur le bleu, aultres sur le vert, choisis ceulx
  <lb>
  </lb>
  qui retirent sur le jaulne pour faire beaulx umbres à
  <m>
   huile
  </m>
  ,
car
  <lb>
  </lb>
  l’umbre mesmem
  <exp>
   ent
  </exp>
  des hommes est jaulnastre. Et pour cet
effect use
  <lb>
  </lb>
  de la
  <m>
   geiete
  </m>
  broyée bien fort, laquelle tu mesleras d’un peu
d’
  <m>
   ocre
   <add>
    jaulne
   </add>
  </m>
  &amp; de
  <lb>
  </lb>
  <m>
   blanc de plomb
  </m>
  . Ou bien aprés que tu as broyé ton
  <m>
   blanc de
plomb
  </m>
  <lb>
  </lb>
  <del>
   bro
  </del>
  et
  <del>
   nettoye p
  </del>
  ramassé avecq la
  <figure id="fig_p065r_1" link="https://drive.google.com/open?id=0B9-oNrvWdlO5UFZyOUNKU3pqVXc" size="x-small">
  </figure>
  ,
  <comment rid="c_065r_01">
  </comment>
  broyes y la
  <m>
   geiette
  </m>
  . Ainsy il
  <lb>
  </lb>
  sera plus desiccatif, &amp; faisant de soy mesme un noir jaulnastre.
  <lb>
  </lb>
  Le peu de blanc meslé le rendra parfaict pour umbre d’homme.
  <lb>
  </lb>
  Les noirs qui font un noir verdastre sont propres pour l’ombre
  <lb>
  </lb>
  des femmes. Prens doncq du noir de
  <gap>
  </gap>
  , un peu de
  <m>
   verd de
   <lb>
   </lb>
   vessie
  </m>
  &amp; du
  <m>
   bistre
  </m>
  , &amp; tu auras un parfaict umbre de
femme à
  <m>
   destrempe
  </m>
  .
 </ab>
 <ab margin="left-middle">
  La pouldre
  <lb>
  </lb>
  de
  <m>
   <pa>
    bled orberé
   </pa>
  </m>
  <lb>
  </lb>
  est plus obscure
  <lb>
  </lb>
  que la
  <m>
   terre
   <lb>
   </lb>
   d’ombre
  </m>
  , &amp; en
  <lb>
  </lb>
  faulte de la
  <lb>
  </lb>
  <m>
   terre d’ombre
  </m>
  <lb>
  </lb>
  ladicte pouldre
  <lb>
  </lb>
  serviroit, mays
  <lb>
  </lb>
  elle n’ha point
  <lb>
  </lb>
  de corps.
 </ab>
</div></entry>