<entry><div categories="wood and its coloring" id="p073r_4">
 Pour faire
 <m>
  boys
 </m>
 gris
 <ab>
  Prenés de l’
  <m>
   alung
  </m>
  avecques de l’
  <m>
   eau de riviere
  </m>
  ,
faictes bouilhir
  <lb>
  </lb>
  ensemble, puis prenés
  <m>
   eau de riviere
  </m>
  aveq du
  <m>
   son
  </m>
  , et
coulés le
  <m>
   son
  </m>
  ,
  <lb>
  </lb>
  et le bouttés ensemble. Prenés
  <m>
   limailhe de fer
  </m>
  &amp; du
  <m>
   souffre
  </m>
  &amp; du
  <lb>
  </lb>
  <m>
   verd de gris
  </m>
  et de la
  <add>
   <m>
    moullée
   </m>
  </add>
  <comment rid="c_073r_03">
  </comment>
  <gap>
  </gap>
  , et
faictes tout boulhir
  <lb>
  </lb>
  ensemble, et bouttés
  <m>
   boys d’
   <pa>
    erable
   </pa>
  </m>
  q
  <exp>
   ui
  </exp>
  aura
trempé dedans l’
  <m>
   eaue
   <lb>
   </lb>
   d’alung
  </m>
  et l’
  <m>
   eaue despuis
  </m>
  , &amp; le mectrés bouillir
ensemble.
  <add>
   Le tout se
   <lb>
   </lb>
   fera mieulx dedans ung
   <tl>
    <m>
     grais
    </m>
   </tl>
   cruzé.
  </add>
 </ab>
</div></entry>