<entry><div continues="yes" id="p115r_1" categories="casting">
  
<head><del>Faire le gect, recuire les <tl>moules</tl>, &amp;c</del><lb/>
   
Advertisseme<exp>n</exp>t sur tout ce<lb/>
   
que dessus <figure size="x-small" id="fig_p115r_5" link="https://drive.google.com/file/d/1ObYzhoh2aRo0KXj3zbaJ08g2z-oNd5CR"/></head>


<ab margin="left-middle" continues="yes">
        
 <figure size="x-small" id="fig_p115r_1" margin="left-middle" link="https://drive.google.com/open?id=0B9-oNrvWdlO5NmVuVUloTy0zNWc">
</figure><comment rid="c_115r_01"/><lb/>
        
si tu veulx, qui sera ass&#233;s,<lb/>

ou bien au deux moicti&#233;s.<lb/>
Mays pource qu&#8217;il fault
</ab>
</div>
 


<div id="p115r_1" part="y">
  
  <ab render="wide">Si ton <al>serpent</al> a est&#233; <tmp>long temps</tmp> sans manger, il advient
   que, quand<lb/>
   
   tu le veulx faire mourir dans l&#8217;<m><bp>urine</bp></m> &amp; <m>vinaigre</m>, il
   s&#8217;emplist de<lb/>
   
   beaucoup d&#8217;<m>eau</m> &amp; s&#8217;enfle, et apr&#233;s il se deseche comme tu le
   plantes &amp;<lb/>
   
   disposes sur la <po>tourtelle</po> d&#8217;<m>ardille</m>, et apr&#233;s il advient que
   quand tu<lb/>
   
   as gect&#233; ton <del><tl>moule</tl></del><m>sable<comment rid="c_115r_05"/> destremp&#233; </m>dessus &amp; qu&#8217;il
   ha faict prise, il se trouve<lb/>
   
   retir&#233; de sorte qu&#8217;entre le <al>serpent</al> &amp; animal il y a une
   petite <ms>ligne</ms> de dista<exp>n</exp>ce,<lb/>
   
   <del>D</del> dans laquelle entre le second <m>sable destremp&#233;</m> gect&#233;.
   <del>M</del> Evite doncques<lb/>
   
   cela si tu peulx. Mays s&#8217;il ne se peult, ne laisse pour cela de
   faire<lb/>
   ton second gect, car le <m>sable</m> qui entrera dans ce vuide sera si
   foible<lb/>
   
   qu&#8217;aisem<exp>ent</exp> il s&#8217;enlevera avecq une <tl>petite poincte</tl>
   &amp; n&#8217;aura poinct faict prise<lb/>
   
   avecq le premier endurcy.</ab>
  
  <ab render="wide">Note qu&#8217;il fault plus d&#8217;<m>alum de plume</m> aux <tl>moules</tl> qui
   se doibvent<lb/>
   
   recuire, co<exp>mm</exp>e ceulx pour l&#8217;<m>or</m> &amp; l&#8217;<m>argent</m>,
   &amp; pour les choses qu&#8217;il fault brusler<lb/>
   
   dedans, qu&#8217;&#224; ceulx qui sont en bonne despouille &amp; qui ne sont que
   pour<lb/>
   
   gecter <m>plomb</m> &amp; <m>estaing</m>. Toutefois en l&#8217;un et l&#8217;autre
   n&#8217;en mects pas<lb/>
   
   trop.</ab>
  
 </div></entry>