<entry><div id="p071v_4" categories="casting">



<head><m>Sable</m></head>

<ab>La <m>moul&#233;e</m> est fort bonne pour gecter en <m>cuivre</m>, mays
il ne<lb/>

fault prendre de <m>celle des <pro>cousteliers</pro></m>, car ce n&#8217;est
que <m>vase</m>,<lb/>

mays de celle que font ceulx qui <del>moulent</del> esmoulent les
grands<lb/>

ciseaulx.</ab>

<ab>Les <m>pierres de filieres</m>,<comment rid="c_071v_01"/> de quoy adoulcissent <pro>ceulx qui
aguisent</pro>,<comment rid="c_071v_02"/><lb/>

moule fort net, estant racl&#233;e, pour le <m>plomb</m>. Elle est
commun<exp>ement</exp><lb/>

de couleur d&#8217;<m>ardoise</m>. On en porte fort &#224;
<pl>Th<exp>ou</exp>l<exp>ous</exp>e</pl> de vers
<pl>Carcassonne</pl>.</ab>

</div></entry>