<root>
<page>133r</page>

<image>http://gallica.bnf.fr/ark:/12148/btv1b10500001g/f271.image</image>

<div>

<id>p133r_1</id>

<head><m>Cire dure</m> pour empraindre<lb/>

cachets</head>

<ab>

Elle se faict de <m>cire blanche</m>, qui est plus dure que
l’aultre,<lb/>

&amp; on y mesle de la <m>ceruse ou blanc de plomb fort
subtillem<exp>ent</exp><lb/>

broyé</m>, tant qu’elle soict assés dure à ta fantasie, <del>u</del> y
mectant<lb/>

une <ms>goutte</ms> de <m>tourmentine</m> pour la lier. Aprés mesles y
telle<lb/>

couleur que tu vouldras. C’est la <m>cire</m> dont les
<pro>orfevres</pro> se<lb/>

servent pour esbaucher.</ab>

</div>

<div>

<id>p133r_2</id>

<head>Pieds de <al>petit<del>s</del>es lezardes</al><lb/>

pour <m>or</m> et <m>argent</m></head>

<ab>

Pource que les pieds de celles qui sont fort petites sont<lb/>

fort subtils, co<exp>mm</exp>e tu as moulé le dessus et que
<del>d</del>tu descouvres<lb/>

le ventre &amp; le dessoubs des pieds, couvre les legerem<exp>ent</exp>
de <m>cire</m><lb/>
&amp; puys gecte le second <tl>moule</tl>. Et la <m>cire</m> s’ostant,
elle laissera<lb/>

un <del>g</del>petit gect pour lesdicts pieds. Et encores que le
dessoubs<lb/>

d’iceulx vienne d’une piece, tu le peulx bien reparer. Et les escailles
<lb/>

de dessus les orteils viendront bien.</ab>

<ab>

<margin>left-middle</margin>

Aulx bouts des ongles<lb/>

<corr>des</corr> <al>grands lesards</al> <add>pose</add><lb/>

<del>fais</del> à chascune<lb/>

un petit rond de<lb/>

<m>cire</m> pour faire<lb/>
le gect, ainsy:</ab>

<figure>

<id>fig_p133r_1</id>

<margin>left-middle</margin>

<link>https://drive.google.com/open?id=0B9-oNrvWdlO5V2JZcWtNeEJmYWs</link>

</figure>

</div>

<div>

<id>p133r_3</id>

<head>

Marques des <tl>poinctes de <m>fil de fer</m></tl><lb/>

qui se trouvent en la teste de l’animal.</head>

<ab>

<del>L</del>Avecq les <tl>poinctes</tl> on ha plustost dressé le plant,
mesmement<lb/>

celuy de la teste. Mays la teste estant percée, il demeure aultour
de<lb/>

la piqueure certaine humeur et petite exudation qui empesche que le<lb/>

sable ne peult bien revestir la <tl>poincte</tl>, &amp; y demeure
tousjours quelque<lb/>

petits pertuis <del>g</del>. Mays pour eviter cela tu pourrois planter
<add>da<exp>n</exp>s la plaste de la<ill/><comment>c_133r_01</comment></add> une<lb/>

<tl>poincte de <m>fer</m></tl> <del>arro</del> esmoussée &amp; arrondie
par le hault bout, &amp; sur ce bout<lb/>

y poser un peu de <m>cire dure</m> ou <del>du</del> un peu de
<m>mastic</m> ou <m>ciment</m>, et par<lb/>

le moyen du <tl><m>fil de fer</m> chault</tl> y faire tenir la gorge de
l’animal,<lb/>

qui se pourroit oster quand tu viendrois à descouvrir le ventre
&amp;<lb/>

la gorge pour faire le second gect.</ab>

</div>

<div>

<id>p133r_4</id>

<head><tl>Crampons</tl> et <tl>moule</tl> rompu</head>

<ab>

Quand tu as fait la premiere recuite &amp; osté les
<tl>crampons</tl>,<lb/>

et que tu <del>les</del> as ouvert ton <tl>moule</tl> pour le nettoyer
en soufla<exp>n</exp>t,<lb/>

sans <m>argent vif</m> qui ne s’employe qu’aulx <tl>moules</tl> clos,
referme le<lb/>

<tl>moule</tl> &amp; remects les <tl>crampons</tl>, mays non pas au
premier lieu où ilz<lb/>

estoient. <m>Relute</m> &amp; reseche. Mays si c’est pour gect
d’<m>argent</m> ou <m>or</m>,<lb/>

<m>lute</m> avec les reste du sable qui ha servy, car c’est le plus
seur. Si ton<lb/>

<tl>moule</tl> en recuisant est rompu, tu le peulx adjouster avec des
<tl>cra<exp>m</exp>pons</tl><lb/>

&amp; <m>luter</m>.</ab>

<ab>

<margin>left-middle</margin>

<mark>X</mark>

</ab>

</div>
</root>
