<root><page>125v</page> 
<image>http://gallica.bnf.fr/ark:/12148/btv1b10500001g/f256.item.r=</image>


<div>
<id>p125v_a1</id>
<head>Viperes et serpens </head>


<ab>
Jay moule une vipere qui pour le gect est des plus propres <lb/>
que nul aultre serpent pource quelle ha belles escailles &amp; <lb/>
bien apparentes par tout le corps &amp; principallem[{ent}] sur la teste <lb/>
et soubs la gorge Elle ha la teste platte le museau rousset <lb/>
tendant a lincarnadin &amp; retrousse co{mm}e laspic cornu ou comme <del>un</del> <lb/>
le dessus du groin dun cochon Grosses machoueres Les yeulx <lb/>
fort pres du museau Et la gueule fort ouverte ou elle <add>ha</add> des <lb/>
dents canines doubles de chasque coste sortant toutes dun tuyau <lb/>
de chair qui les couvre et revest Elle ha aussy dans la <lb/>
gorge un tuyau de chair faict comme la verge dun chien <lb/>
dou sort son fisson Les aultres serpents ont double <lb/>
reng de dents </ab>
 
<ab>
<margin>left-top</margin>

Si tu veulx <del>couper</del> <lb/>
<del>les</del> mouler les serpents <lb/>
la gueule ouverte <lb/>
il fault couper la <lb/>
teste &amp; la laisser <lb/>
dedans car elle <lb/>
ne seroit pas en <lb/>
despouille </ab>
 
</div>
<div>
<id>p125v_a2</id>
<head> Mouler tortues </head>


<ab>
Cest une matiere particuliere du gect des serpents &amp; <lb/>
herbes et fleurs pourceque les cavites qui sont entre <lb/>
les deulx coquilles requierent plusieurs pieces Elles <lb/>
se moulent de <m>plastre</m> pour gecter en sucre sans faire gect <lb/>
co{mm}e font toutes choses que tu vouldras </ab>
 
</div>
<div>
<id>p125v_a3</id>
<head>
<m>Plastre</m> pour gect de <m>cire</m> </head>


<ab>
Quand tu veulx gecter en <m>cire</m> dans le moule de <m>plastre</m> <lb/>
il fault que tu sçaiches pour secret quil est besoing <lb/>
que ton moule soict dans l<m>eau chaulde</m> Jamays lanimal <lb/>
ne vient si net quen metal pourceque la <m>cire</m> grippe Mays <lb/>
cest pour esbaucher animal au plus pres du naturel <del>Et</del> <lb/>
pour apres le reparer Il en fault bien oster toutes les <lb/>
escailles <del>Quand</del> <add>Car</add> la cire y entreroit &amp; ne se despouilleroit <lb/>
pas En moulant aussy lanimal Abas les escaille pour cire <lb/>
&amp; au contraire frotte les au rebours affin quelles seslevent <lb/>
pour animaulx car elles sen monstrent mieulx Nattend pas <lb/>
aussy a despouiller ta <del>cire</del> quelle soict <del>un peu</del> du tout <lb/>
refroidie Mays pendant quelle est un peu chaulde <lb/>
Quand tu as aussy moule le premier gect de lanimal <lb/>
descouvre le bien la moictie Affin quil soit en despouille <lb/>
Y en ayant aultant dans un moule quen laultre Fais aussy <lb/>
force gects larges sentretenant a lanimal affin de le fortifier <lb/>
en se despouillant &amp; apres tu couppes cela </ab>
 
<margin>left-bottom</margin>
<ab>
<figure>+</figure> <lb/>
L<m>albastre</m> <lb/>
co{mmun}ement apelle qui <lb/>
touteffois est <lb/>
<m>plastre</m> est bien <lb/>
dur mays il se <lb/>
retire fort Il est <lb/>
bien bon pour en <lb/>
fayre medaille <lb/>
Mays il veult <lb/>
estre fort subtillem{ent} <lb/>
passe </ab>
</div></root>