<root><page>139r</page> 
<image>http://gallica.bnf.fr/ark:/12148/btv1b10500001g/f283.image</image>


<div>
<id>p139r_1</id>
<head>Gect de <m>plomb</m> et d<m>estaim</m></head>


<ab>
Quand il est souvent fondu il saigrist &amp; rend <del>fe</del><lb/>
frangible pourcequil se gecte fort chault &amp; se rend demy<lb/>
calcine<lb/>
use doncq<lb/>
du noeuf</ab>


<ab>La ligne que jay pratiquee pour <al>lesards</al> &amp; <al>serpents</al><lb/>
cest deulx ℥ d<m>estaim fin</m> sur une lb de <m>plomb naeif</m> &amp;non<lb/>
sophistique Le moule se faict du sable susdict commun<lb/>
a touct <m>metaulx</m> co{mm}e il est recuit le laisses froidir jusques<lb/>
a ce que tu puisses tenir le doigt sans laesion dans le trou<lb/>
du gect  Quand au <m>plomb</m> on le fond dans un crusol <del>ju</del><lb/>
a foeu de souflets jusques a ce que le crusol &amp; le <m>plomb</m><lb/>
soict rouge Comme il est en cet estat repurge le de <m>charbon</m><lb/>
ou avecq un raclouer faict a propos ou avecq le vent du<lb/>
petit souflet Ce faict laisse le poser ainsy rouge &amp;<lb/>
recuire en soymesme un peu puys gecte y si tu veulx un pe<lb/>
de <m>rousine</m> pour brusler la crasse Touteffoys aulcuns<lb/>
trouvent mieulx de ny en mectre poinct a cause quelle laisse<lb/>
crasse Mays co{mm}e ilz sont prests a gecter il ne fault pas<lb/>
quilz oublyent de gecter dedans aussy gros quune ferve<lb/>
d<m>estain de glace</m> sur chasque lb de <m>plomb</m> Et quel soict<lb/>
rouge co{mm}e <m>metal</m> fondu quand il entre dans le moule Et<lb/>
si le moule est grand il est mieulx de le mectre en une presse<lb/>
affin quil se joigne bien &amp; que le <m>plomb</m> ne sespanche<lb/>
poinct hors du molle Touteffois si cela advenoit &amp;<lb/>
que pour la premiere ou deux ou troisiesme fois<lb/>
ton moule ne fust pas remply Gecte hardiment car<lb/>
pourveu que ton <m>metal</m> soict rouge il se reprendra &amp; joindra<lb/>
avecq laultre Et viendra tresnet co{mm}e le principal<lb/>
Le mesme se peult dire de l<m>estain fin</m> pour les choses<lb/>
tanvres Et la ligne de l<m>estain fin</m> cest dune ℥ de <m>plomb<lb/>
neuf</m> sur une lb diceluy Les grands moules se doibvent<lb/>
mectre en presses bien serres entre deulx planches de <m>cuivre</m><lb/>
<del>pu</del> &amp; puys les ensevelir dans le sable qui est meilleur que<lb/>
les <m>cendres</m> pourceque <del>il est</del> par sa poisanteur il selle mieulx<lb/>
Aultrem{ent} ses grands moules sont subgects a sentrouvrir par<lb/>
la poisanteur du <m>metal</m> Aulcuns font un pot quarre</ab>


<ab>
<margin>left-top</margin>
Quand la medaille est espesse<lb/>
on nest pas astraint de gecter<lb/>
si chault que quand elle est<lb/>
tanvre</ab>


<ab>
<margin>left-top</margin>
<figure>+</figure>
Note que si tu<lb/>
les veulx gecter<lb/>
en <m>os de seiche</m><lb/>
il ne fault pas<lb/>
quilz soient gueres<lb/>
chaulx pourcequilz<lb/>
brusleroient l<m>os<lb/>
de seiche</m> Essaye<lb/>
pour cet effect<lb/>
avecq du <m>papier</m><lb/>
sil roussist<lb/>
le <m>papier</m> cest<lb/>
asses il est bon<lb/>
a gecter mays<lb/>
sil noircist le<lb/>
<m>papier</m> il est<lb/>
trop chault</ab>
   
<ab>
<margin>left-bottom</margin>
Si tu veulx<lb/>
gecter un foeillet<lb/>
escript fais ta<lb/>
ligne de <del>plom</del><lb/>
moictie <m>plomb</m> &amp;<lb/>
moictie <m>estain</m> &amp;<lb/>
aussy tost quil<lb/>
sera fondu gecte<lb/>
entre deulx <m>cartons</m><lb/>
en lieu fort plain<lb/>
&amp; au niveau &amp; avecq<lb/>
une poincte d<m>or</m><lb/>
ou de <m>boys</m> dur<lb/>
grave a gaulche<lb/>
lescripture quil<lb/>
te plaist Et<lb/>
ayant verse<lb/>
le <m>plomb</m> sur<lb/>
un <m>carton</m> presse<lb/>
dessus avecq<lb/>
laultre <m>carton</m><lb/>
adapte</ab>


<cont/>
</div></root>