<root><page>164r</page>
<image>http://gallica.bnf.fr/ark:/12148/btv1b10500001g/f333.item</image>


<div>
<id>p164r_1</id>
<head>Gect</head>


<ab>
Quand tu fais le gect de quelque animal delicat<lb/>
co{mm}e dun <al>serpent</al> fair quil vienne du coste du ventre<lb/>
&amp; sous la queue Car de coste il ny ha que des<lb/>
ligne droictes qui sont aysees a reparer plus beaucoup<lb/>
que le dos qui est plus en vene &amp; plus marque</ab>
</div>
  
<div>
<id>p164r_2</id>
<head>Repares les baves</head>


<ab>
Les ayant doulcem{ent} oster avelq la poincte du<lb/>
<tl>chaple</tl> ou du <tl>burin</tl> racle les avelq laile du <tl>burin</tl><lb/>
ou doulcem{ent} avelq un petite <tl>lime</tl> &amp; frotte de <m>charbon<lb/>
de <pa>saule</pa></m> &amp; les petites broisses Continue aussy les<lb/>
lignes interrompant pas les baves</ab>
</div>


<div>
<id>p164r_3</id>
<head><m>Argent</m> <m>plombeus</m></head>


<ab>
Il se dechet beaucoup a cause que le <m>plomb</m> qui<lb/>
y est mesle le travaille co{mm}e en la copolle et le faict<lb/>
saulter en petit grains aulx bords du <tl>creuset</tl><lb/>
&amp; sur le <m>charbon</m> qui le couvre Il est aussy gras<lb/>
Et par ainsy il est bon de fondre tout <m>argent</m><lb/>
monnoye co{mm}e de <cn>realles</cn> &amp; aultres &amp; le mectes en<lb/> 
lingot plustost que le fondre pour gecter les<lb/>
<al>lesardes</al> &amp; <al>animaulx</al> Car il vient mieux Jen ay<lb/>
moule net co{mme} le principal ainsy une petite<lb/>
<al>vipere</al> d<m>argent</m> Et fis la ligne de 4 <cn>realles</cn><lb/>
de 20 <cn>S{ol}</cn> d<pl>espaigne</pl> &amp; une piece de xx <cn>S{ol}</cn> de<lb/>
<pl>france</pl></ab>
</div>
  
<div>
<id>164r_4</id>
<head>Soufler</head>


<ab>
Quand tu fonds de l<m>argent</m> &amp; de l<m>or</m> ne soufle pas fort<lb/>
&amp; de violence pourceque le <m>charbon</m> se passant le <tl>crusole</tl><lb/>
sabaisseroit &amp; <del>larg</del> se pourrois renverser Mays quand<lb/>
ton <tl>moule</tl> sera prest lors soufle fort pour bien eschaufer<lb/>
l<m>argent</m> ou l<m>or</m> Tous deulx estant fondus veulent estre<lb/>
souffles par dessus avecq un petit <tl>souflet</tl> Mesmem{ent} l<m>or</m> Car cela<lb/>
leur oste leurs fumees &amp; les adoulcist</ab>
</div></root>