<entry><div id="p040r_2" categories="corrosives">



<head><m>Eau fort</m></head>

<ab>Aulcuns mectent <del>sur</del> <add>pour</add> quatre <ms>lb</ms> de
matieres d<m>eau fort</m> <del>quattre</del><lb/>

qui sont dans la <tl>cornue</tl> quattre <ms>onces</ms> d<m>eau
commune</m> dans le<lb/>

<tl>recipient</tl> qui est mieulx que le mectre dans la <tl>cornue</tl>
On faict<lb/>

deflegmer &amp; calciner l<m>alum</m> affin que l<m>eau</m> naye pas
tant de<lb/>

feces plusieurs la font sans deflegmer l<m>alum</m></ab>

</div>

</entry>