<entry><div categories="casting" id="p133v_2">
 Chose qui nest en despouille
 <ab>
  Il la fault couper pour la faire brusler dans le
  <tl>
   moule
  </tl>
  <lb>
  </lb>
  mays couppe la avecq des
  <tl>
   ciseaux
  </tl>
  tout dun coup affin que
  <lb>
  </lb>
  le
  <m>
   sang
  </m>
  ne tombe sur le
  <tl>
   moule
  </tl>
  &amp; ne fasse
  <m>
   crasse
  </m>
  qui estant
  <lb>
  </lb>
  recuite est difficille a oster. Mects apres ton
  <tl>
   moule
  </tl>
  dans
  <lb>
  </lb>
  le
  <tl>
   four
  </tl>
  ou semblable chaleur affin que promptem
  <exp>
   ent
  </exp>
  cela se
  <lb>
  </lb>
  seche &amp; se retire plustost que faire crouste sur le
  <tl>
   moule
  </tl>
  <lb>
  </lb>
  ou
  <m>
   moisissure
  </m>
 </ab>
 <ab margin="left-middle" render="tall">
  <mark>
   +
  </mark>
  <lb>
  </lb>
  Quand tu moules de
  <lb>
  </lb>
  <al>
   petites lesardes
  </al>
  et que
  <lb>
  </lb>
  tu veux descouvrir
  <lb>
  </lb>
  la premiere partye
  <lb>
  </lb>
  moulee commance a
  <lb>
  </lb>
  descouvrir les testes
  <lb>
  </lb>
  &amp; tu cognoistras
  <lb>
  </lb>
  lendroit dicelle par
  <lb>
  </lb>
  l
  <tl>
   espingle
  </tl>
  <lb>
  </lb>
  Ne touche point a
  <lb>
  </lb>
  descouvrir les pattes
  <lb>
  </lb>
  que tu nayes descouvert
  <lb>
  </lb>
  tout le corps affin
  <lb>
  </lb>
  que le corps desnue se
  <lb>
  </lb>
  remuant ne fasse
  <lb>
  </lb>
  oster les pattes de leur
  <lb>
  </lb>
  place ou il est fascheux
  <lb>
  </lb>
  de les remectre
  <lb>
  </lb>
  Quand tu ostes les
  <lb>
  </lb>
  <tl>
   petites poinctes
  </tl>
  qui
  <lb>
  </lb>
  tiennent les pattes
  <lb>
  </lb>
  arreste les &amp; les presse
  <lb>
  </lb>
  de quelque chose affin
  <lb>
  </lb>
  quen osta
  <exp>
   n
  </exp>
  t l
  <tl>
   espingle
  </tl>
  <lb>
  </lb>
  elles ne sostent de
  <lb>
  </lb>
  leur place ou en fin
  <lb>
  </lb>
  tu les peux remectre
  <lb>
  </lb>
  avecq de la
  <m>
   cire
  </m>
 </ab>
</div></entry>